agentsphere_desktop/__init__.py
agentsphere_desktop/main.py
agentsphere_desktop-0.1.1.dist-info/LICENSE
agentsphere_desktop-0.1.1.dist-info/METADATA
agentsphere_desktop-0.1.1.dist-info/WHEEL
agentsphere_desktop-0.1.1.dist-info/RECORD
