Metadata-Version: 2.3
Name: agentsphere-desktop
Version: 0.1.1
Summary: Agentsphere Desktop
License: MIT
Author: agentsphere
Author-email: hello@agentsphere.eun
Requires-Python: >=3.9,<4.0
Classifier: License :: OSI Approved :: MIT License
Classifier: Programming Language :: Python :: 3
Classifier: Programming Language :: Python :: 3.9
Classifier: Programming Language :: Python :: 3.10
Classifier: Programming Language :: Python :: 3.11
Classifier: Programming Language :: Python :: 3.12
Classifier: Programming Language :: Python :: 3.13
Requires-Dist: agentsphere (>=0.1.2,<0.2.0)
Requires-Dist: pillow (>=11.1.0,<12.0.0)
Requires-Dist: requests (>=2.32.3,<3.0.0)
Project-URL: Bug Tracker, https://github.com/agentsphere/desktop/issues
Project-URL: Homepage, https://agentsphere.run/
Project-URL: Repository, https://github.com/agentsphere
